docstringargs.py
docstringargs-0.2.1.dist-info/METADATA
docstringargs-0.2.1.dist-info/WHEEL
docstringargs-0.2.1.dist-info/metadata.json
docstringargs-0.2.1.dist-info/top_level.txt
docstringargs-0.2.1.dist-info/DESCRIPTION.rst
docstringargs-0.2.1.dist-info/RECORD
