Metadata-Version: 2.0
Name: docstringargs
Version: 0.2.1
Summary: Argparse builder using function docstrings
Home-page: https://github.com/Rosuav/docstringargs
Author: Chris Angelico
Author-email: rosuav@gmail.com
License: MIT
Keywords: argparse
Platform: UNKNOWN
Classifier: Development Status :: 3 - Alpha
Classifier: Intended Audience :: Developers
Classifier: Topic :: Software Development :: Libraries
Classifier: License :: OSI Approved :: MIT License
Classifier: Programming Language :: Python :: 2
Classifier: Programming Language :: Python :: 2.7
Classifier: Programming Language :: Python :: 3
Classifier: Programming Language :: Python :: 3.4
